{
  "id": "FAQ-04",
  "title": "Focused home loan ask uses Desk FAQ",
  "builder_id": "brigade-group",
  "tags": ["quality", "faq", "closed-beta"],
  "turns": [
    { "text": "hi" },
    { "text": "apartment in North Bangalore" },
    { "text": "Brigade Eldorado", "assert": { "reply_includes": ["eldorado"] } },
    {
      "text": "can I get a home loan?",
      "assert": {
        "reply_includes": ["loan"],
        "reply_excludes": ["want pricing, legal details"],
        "tools_include": ["faqLookup"]
      }
    }
  ]
}
